hypnus/__init__.py
hypnus/main.py
hypnus/power.py
hypnus/tempo.py
hypnus-1.0.0.dist-info/LICENSE
hypnus-1.0.0.dist-info/METADATA
hypnus-1.0.0.dist-info/WHEEL
hypnus-1.0.0.dist-info/entry_points.txt
hypnus-1.0.0.dist-info/RECORD
