Metadata-Version: 2.1
Name: hypnus
Version: 1.0.0
Summary: Power off computer on EDF Tempo red days.
Home-page: https://github.com/guillaumedsde/hypnus
License: MIT
Keywords: shutdown,EDF,tempo
Author: guillaumedsde
Author-email: 30023543+guillaumedsde@users.noreply.github.com
Requires-Python: >=3.8,<3.13
Classifier: Development Status :: 3 - Alpha
Classifier: Intended Audience :: Information Technology
Classifier: License :: OSI Approved :: MIT License
Classifier: Operating System :: Microsoft :: Windows
Classifier: Operating System :: POSIX
Classifier: Programming Language :: Python :: 3
Classifier: Programming Language :: Python :: 3.8
Classifier: Programming Language :: Python :: 3.9
Classifier: Programming Language :: Python :: 3.10
Classifier: Programming Language :: Python :: 3.11
Classifier: Programming Language :: Python :: 3.12
Classifier: Topic :: System :: Shells
Project-URL: Repository, https://github.com/guillaumedsde/hypnus
